{"directed": false, "multigraph": false, "graph": {}, "nodes": [{"id": "nanocrystal"}, {"id": "juncu"}, {"id": "cellulose"}, {"id": "agent"}, {"id": "hydrolysi"}, {"id": "plant"}, {"id": "stem"}, {"id": "acid"}], "links": [{"weight": 0.25, "source": "nanocrystal", "target": "juncu"}, {"weight": 1.0, "source": "nanocrystal", "target": "cellulose"}, {"weight": 0.4, "source": "nanocrystal", "target": "agent"}, {"weight": 0.3333333333333333, "source": "nanocrystal", "target": "hydrolysi"}, {"weight": 0.2222222222222222, "source": "juncu", "target": "cellulose"}, {"weight": 0.2222222222222222, "source": "juncu", "target": "agent"}, {"weight": 0.2, "source": "juncu", "target": "hydrolysi"}, {"weight": 4.0, "source": "juncu", "target": "plant"}, {"weight": 0.2, "source": "cellulose", "target": "stem"}, {"weight": 0.2857142857142857, "source": "cellulose", "target": "agent"}, {"weight": 0.4, "source": "cellulose", "target": "hydrolysi"}, {"weight": 0.2857142857142857, "source": "agent", "target": "hydrolysi"}, {"weight": 1.0, "source": "hydrolysi", "target": "acid"}, {"weight": 1.0, "source": "plant", "target": "stem"}, {"weight": 0.14285714285714285, "source": "stem", "target": "acid"}]}