{"directed": false, "multigraph": false, "graph": {}, "nodes": [{"id": "trace"}, {"id": "morocco"}, {"id": "elements"}, {"id": "community"}, {"id": "bacteria"}, {"id": "soil"}, {"id": "pgs"}, {"id": "risk"}, {"id": "health"}, {"id": "quality"}, {"id": "space"}, {"id": "public"}, {"id": "green"}], "links": [{"weight": 0.3333333333333333, "source": "trace", "target": "morocco"}, {"weight": 1.0, "source": "trace", "target": "elements"}, {"weight": 0.2, "source": "trace", "target": "community"}, {"weight": 0.2, "source": "trace", "target": "bacteria"}, {"weight": 0.5, "source": "trace", "target": "soil"}, {"weight": 0.3333333333333333, "source": "morocco", "target": "pgs"}, {"weight": 0.16666666666666666, "source": "morocco", "target": "community"}, {"weight": 0.16666666666666666, "source": "morocco", "target": "bacteria"}, {"weight": 0.5, "source": "morocco", "target": "soil"}, {"weight": 0.2, "source": "elements", "target": "bacteria"}, {"weight": 0.3333333333333333, "source": "elements", "target": "health"}, {"weight": 0.25, "source": "community", "target": "bacteria"}, {"weight": 0.2, "source": "community", "target": "soil"}, {"weight": 0.25, "source": "bacteria", "target": "soil"}, {"weight": 0.25, "source": "bacteria", "target": "health"}, {"weight": 0.5, "source": "soil", "target": "risk"}, {"weight": 1.0, "source": "soil", "target": "quality"}, {"weight": 0.6666666666666666, "source": "soil", "target": "pgs"}, {"weight": 1.0, "source": "pgs", "target": "quality"}, {"weight": 1.0, "source": "pgs", "target": "space"}, {"weight": 2.0, "source": "risk", "target": "health"}, {"weight": 1.0, "source": "space", "target": "green"}, {"weight": 1.0, "source": "public", "target": "green"}]}